yosegi/__init__.py
yosegi/__main__.py
yosegi-0.1.0.dist-info/WHEEL
yosegi-0.1.0.dist-info/entry_points.txt
yosegi-0.1.0.dist-info/METADATA
yosegi-0.1.0.dist-info/RECORD
