Metadata-Version: 2.3
Name: yosegi
Version: 0.1.0
Summary: Pyramid (Geo)Parquet Generator
Requires-Dist: duckdb>=1.4.3
Requires-Dist: pandas>=2.3.3
Requires-Python: >=3.14
